mylib_026/__init__.py
mylib_026-0.1.dist-info/LICENSE.txt
mylib_026-0.1.dist-info/METADATA
mylib_026-0.1.dist-info/WHEEL
mylib_026-0.1.dist-info/top_level.txt
mylib_026-0.1.dist-info/RECORD
